{
  "schema": "mesaha-suite-legacy-backups-v20",
  "generated_at": "2026-07-14T19:45:00+03:00",
  "folder_id": "1-zpEVeLMzW_DnH44_DuJrNfuAXnXK5vk",
  "folder_url": "https://drive.google.com/drive/folders/1-zpEVeLMzW_DnH44_DuJrNfuAXnXK5vk?usp=drive_link",
  "public": true,
  "total": 30,
  "files": [
    {
      "id": "1vECP4TpClC-Gnr8axTLPlYnN3oFi71D9",
      "file_name": "Mesaha_IO_MUSTAFA SARI_Alahan_300_20260714_171730.json",
      "username": "MUSTAFA SARI",
      "seflik": "Alahan",
      "bolme": "300",
      "backup_date": "20260714",
      "backup_time": "171730",
      "created_at": "2026-07-14T14:17:30.709Z",
      "size_bytes": 89746,
      "view_url": "https://drive.google.com/file/d/1vECP4TpClC-Gnr8axTLPlYnN3oFi71D9/view",
      "download_url": "https://drive.google.com/uc?export=download&id=1vECP4TpClC-Gnr8axTLPlYnN3oFi71D9"
    },
    {
      "id": "162lngiEkOTUfqwKWDW05S-n6qetJ4yUd",
      "file_name": "Mesaha_IO_İsmail Işık_Tunçbilek_222_20260713_171653.json",
      "username": "İsmail Işık",
      "seflik": "Tunçbilek",
      "bolme": "222",
      "backup_date": "20260713",
      "backup_time": "171653",
      "created_at": "2026-07-13T14:16:54.254Z",
      "size_bytes": 159047,
      "view_url": "https://drive.google.com/file/d/162lngiEkOTUfqwKWDW05S-n6qetJ4yUd/view",
      "download_url": "https://drive.google.com/uc?export=download&id=162lngiEkOTUfqwKWDW05S-n6qetJ4yUd"
    },
    {
      "id": "1RDnVi8o7lerPrzQYJzxkOsJZ20atU__R",
      "file_name": "Mesaha_IO_Yakup Düzgün_Yaylacık_351_20260713_142332.json",
      "username": "Yakup Düzgün",
      "seflik": "Yaylacık",
      "bolme": "351",
      "backup_date": "20260713",
      "backup_time": "142332",
      "created_at": "2026-07-13T11:23:32.835Z",
      "size_bytes": 374653,
      "view_url": "https://drive.google.com/file/d/1RDnVi8o7lerPrzQYJzxkOsJZ20atU__R/view",
      "download_url": "https://drive.google.com/uc?export=download&id=1RDnVi8o7lerPrzQYJzxkOsJZ20atU__R"
    },
    {
      "id": "17GI3xlMeFRPqjihPfgz5loHKgv9FXYJt",
      "file_name": "Mesaha_IO_Alperen Taha Sökmen_Tunçbilek_84_20260713_122814.json",
      "username": "Alperen Taha Sökmen",
      "seflik": "Tunçbilek",
      "bolme": "84",
      "backup_date": "20260713",
      "backup_time": "122814",
      "created_at": "2026-07-13T09:28:15.155Z",
      "size_bytes": 88777,
      "view_url": "https://drive.google.com/file/d/17GI3xlMeFRPqjihPfgz5loHKgv9FXYJt/view",
      "download_url": "https://drive.google.com/uc?export=download&id=17GI3xlMeFRPqjihPfgz5loHKgv9FXYJt"
    },
    {
      "id": "1adyqmglsNUWuXG2h-nO5cTgCHJWNHtHJ",
      "file_name": "Mesaha_IO_Yakup Düzgün_Yaylacık_351_20260713_003531.json",
      "username": "Yakup Düzgün",
      "seflik": "Yaylacık",
      "bolme": "351",
      "backup_date": "20260713",
      "backup_time": "003531",
      "created_at": "2026-07-12T21:35:31.804Z",
      "size_bytes": 374796,
      "view_url": "https://drive.google.com/file/d/1adyqmglsNUWuXG2h-nO5cTgCHJWNHtHJ/view",
      "download_url": "https://drive.google.com/uc?export=download&id=1adyqmglsNUWuXG2h-nO5cTgCHJWNHtHJ"
    },
    {
      "id": "1oxDdLjykyZNeq7ieKGJNwWwHfTNg59Vp",
      "file_name": "Mesaha_IO_Alperen Taha Sökmen_Tunçbilek_84_20260712_150526.json",
      "username": "Alperen Taha Sökmen",
      "seflik": "Tunçbilek",
      "bolme": "84",
      "backup_date": "20260712",
      "backup_time": "150526",
      "created_at": "2026-07-12T12:05:27.163Z",
      "size_bytes": 2331,
      "view_url": "https://drive.google.com/file/d/1oxDdLjykyZNeq7ieKGJNwWwHfTNg59Vp/view",
      "download_url": "https://drive.google.com/uc?export=download&id=1oxDdLjykyZNeq7ieKGJNwWwHfTNg59Vp"
    },
    {
      "id": "11Gis2UdJ5-RezOrf6DuVYDZ-YjckIKd_",
      "file_name": "Mesaha_IO_Yakup Düzgün_Yaylacık_351_20260712_135604.json",
      "username": "Yakup Düzgün",
      "seflik": "Yaylacık",
      "bolme": "351",
      "backup_date": "20260712",
      "backup_time": "135604",
      "created_at": "2026-07-12T10:56:04.819Z",
      "size_bytes": 262042,
      "view_url": "https://drive.google.com/file/d/11Gis2UdJ5-RezOrf6DuVYDZ-YjckIKd_/view",
      "download_url": "https://drive.google.com/uc?export=download&id=11Gis2UdJ5-RezOrf6DuVYDZ-YjckIKd_"
    },
    {
      "id": "1GEPBvbXfuntts1V4IsdfeGFW0sEjEdB8",
      "file_name": "Mesaha_IO_Yakup_Yaylacık_351_20260712_101709.json",
      "username": "Yakup",
      "seflik": "Yaylacık",
      "bolme": "351",
      "backup_date": "20260712",
      "backup_time": "101709",
      "created_at": "2026-07-12T07:17:10.505Z",
      "size_bytes": 262330,
      "view_url": "https://drive.google.com/file/d/1GEPBvbXfuntts1V4IsdfeGFW0sEjEdB8/view",
      "download_url": "https://drive.google.com/uc?export=download&id=1GEPBvbXfuntts1V4IsdfeGFW0sEjEdB8"
    },
    {
      "id": "1qeS2hsOAe24-SnyPotlT52LeJijudwbo",
      "file_name": "Mesaha_IO_Yakup_Yaylacık_bolme_20260711_215808.json",
      "username": "Yakup",
      "seflik": "Yaylacık",
      "bolme": "bolme",
      "backup_date": "20260711",
      "backup_time": "215808",
      "created_at": "2026-07-11T18:58:08.800Z",
      "size_bytes": 5638,
      "view_url": "https://drive.google.com/file/d/1qeS2hsOAe24-SnyPotlT52LeJijudwbo/view",
      "download_url": "https://drive.google.com/uc?export=download&id=1qeS2hsOAe24-SnyPotlT52LeJijudwbo"
    },
    {
      "id": "1nuGeShgU-m-_U0e2IYMD93PUz2EWfQUA",
      "file_name": "Mesaha_IO_YeşilKurt43_Yaylacık_351_20260711_203708.json",
      "username": "YeşilKurt43",
      "seflik": "Yaylacık",
      "bolme": "351",
      "backup_date": "20260711",
      "backup_time": "203708",
      "created_at": "2026-07-11T17:37:08.926Z",
      "size_bytes": 263585,
      "view_url": "https://drive.google.com/file/d/1nuGeShgU-m-_U0e2IYMD93PUz2EWfQUA/view",
      "download_url": "https://drive.google.com/uc?export=download&id=1nuGeShgU-m-_U0e2IYMD93PUz2EWfQUA"
    },
    {
      "id": "1go8D2bZN5zyc0tMMNPH79C-bEnZ0mkly",
      "file_name": "Mesaha_IO_Emrah_Kuzukulağı_168_20260711_172656.json",
      "username": "Emrah",
      "seflik": "Kuzukulağı",
      "bolme": "168",
      "backup_date": "20260711",
      "backup_time": "172656",
      "created_at": "2026-07-11T14:26:57.404Z",
      "size_bytes": 1363,
      "view_url": "https://drive.google.com/file/d/1go8D2bZN5zyc0tMMNPH79C-bEnZ0mkly/view",
      "download_url": "https://drive.google.com/uc?export=download&id=1go8D2bZN5zyc0tMMNPH79C-bEnZ0mkly"
    },
    {
      "id": "1yirJlOCQb52KSyzvYPHj-5HYzcCb7Cr0",
      "file_name": "Mesaha_IO_Onur_Oğuzlar_34_20260711_141004.json",
      "username": "Onur",
      "seflik": "Oğuzlar",
      "bolme": "34",
      "backup_date": "20260711",
      "backup_time": "141004",
      "created_at": "2026-07-11T11:10:04.733Z",
      "size_bytes": 31163,
      "view_url": "https://drive.google.com/file/d/1yirJlOCQb52KSyzvYPHj-5HYzcCb7Cr0/view",
      "download_url": "https://drive.google.com/uc?export=download&id=1yirJlOCQb52KSyzvYPHj-5HYzcCb7Cr0"
    },
    {
      "id": "1I7BRJMFO813gdJwwKK57JwNI3udk3f1G",
      "file_name": "Mesaha_IO_Onur_Oğuzlar_34_20260711_134927.json",
      "username": "Onur",
      "seflik": "Oğuzlar",
      "bolme": "34",
      "backup_date": "20260711",
      "backup_time": "134927",
      "created_at": "2026-07-11T10:49:27.895Z",
      "size_bytes": 38060,
      "view_url": "https://drive.google.com/file/d/1I7BRJMFO813gdJwwKK57JwNI3udk3f1G/view",
      "download_url": "https://drive.google.com/uc?export=download&id=1I7BRJMFO813gdJwwKK57JwNI3udk3f1G"
    },
    {
      "id": "1PvDx3JzWwM5THoI0w1zVK58XkhMQ97zq",
      "file_name": "Mesaha_IO_Onur_Oğuzlar_34_20260711_134754.json",
      "username": "Onur",
      "seflik": "Oğuzlar",
      "bolme": "34",
      "backup_date": "20260711",
      "backup_time": "134754",
      "created_at": "2026-07-11T10:47:54.773Z",
      "size_bytes": 33503,
      "view_url": "https://drive.google.com/file/d/1PvDx3JzWwM5THoI0w1zVK58XkhMQ97zq/view",
      "download_url": "https://drive.google.com/uc?export=download&id=1PvDx3JzWwM5THoI0w1zVK58XkhMQ97zq"
    },
    {
      "id": "1IuyGjoMeZZn5yHFPkZWOdoytX_wXNN5O",
      "file_name": "Mesaha_IO_Onur_Oğuzlar_34_20260711_132047.json",
      "username": "Onur",
      "seflik": "Oğuzlar",
      "bolme": "34",
      "backup_date": "20260711",
      "backup_time": "132047",
      "created_at": "2026-07-11T10:20:48.613Z",
      "size_bytes": 32635,
      "view_url": "https://drive.google.com/file/d/1IuyGjoMeZZn5yHFPkZWOdoytX_wXNN5O/view",
      "download_url": "https://drive.google.com/uc?export=download&id=1IuyGjoMeZZn5yHFPkZWOdoytX_wXNN5O"
    },
    {
      "id": "1mJV4tSGCYKZDTElcKtUm5mTVgmAAOPiH",
      "file_name": "Mesaha_IO_Onur_Oğuzlar_34_20260711_132004.json",
      "username": "Onur",
      "seflik": "Oğuzlar",
      "bolme": "34",
      "backup_date": "20260711",
      "backup_time": "132004",
      "created_at": "2026-07-11T10:20:05.454Z",
      "size_bytes": 32635,
      "view_url": "https://drive.google.com/file/d/1mJV4tSGCYKZDTElcKtUm5mTVgmAAOPiH/view",
      "download_url": "https://drive.google.com/uc?export=download&id=1mJV4tSGCYKZDTElcKtUm5mTVgmAAOPiH"
    },
    {
      "id": "1ssNOHRWumeG5Anoeov_ggQ2XjVo22dyD",
      "file_name": "Mesaha_IO_Onur_Oğuzlar_34_20260711_125135.json",
      "username": "Onur",
      "seflik": "Oğuzlar",
      "bolme": "34",
      "backup_date": "20260711",
      "backup_time": "125135",
      "created_at": "2026-07-11T09:51:35.795Z",
      "size_bytes": 27254,
      "view_url": "https://drive.google.com/file/d/1ssNOHRWumeG5Anoeov_ggQ2XjVo22dyD/view",
      "download_url": "https://drive.google.com/uc?export=download&id=1ssNOHRWumeG5Anoeov_ggQ2XjVo22dyD"
    },
    {
      "id": "1wRqFGbMmblKuyJE0nUMCVkkYVY_BiR1i",
      "file_name": "Mesaha_IO_oğuzhan_yaylacık_351_20260711_123151.json",
      "username": "oğuzhan",
      "seflik": "yaylacık",
      "bolme": "351",
      "backup_date": "20260711",
      "backup_time": "123151",
      "created_at": "2026-07-11T09:31:51.691Z",
      "size_bytes": 262081,
      "view_url": "https://drive.google.com/file/d/1wRqFGbMmblKuyJE0nUMCVkkYVY_BiR1i/view",
      "download_url": "https://drive.google.com/uc?export=download&id=1wRqFGbMmblKuyJE0nUMCVkkYVY_BiR1i"
    },
    {
      "id": "1NVV5X9Y9wkrt69q4z-nlMilNCPMoO5oH",
      "file_name": "Mesaha_IO_Onur_Oğuzlar_34_20260711_121643.json",
      "username": "Onur",
      "seflik": "Oğuzlar",
      "bolme": "34",
      "backup_date": "20260711",
      "backup_time": "121643",
      "created_at": "2026-07-11T09:16:44.055Z",
      "size_bytes": 29515,
      "view_url": "https://drive.google.com/file/d/1NVV5X9Y9wkrt69q4z-nlMilNCPMoO5oH/view",
      "download_url": "https://drive.google.com/uc?export=download&id=1NVV5X9Y9wkrt69q4z-nlMilNCPMoO5oH"
    },
    {
      "id": "1NXgFpuzxtRcAtlAXxXIcsVMGArcrUbA9",
      "file_name": "Mesaha_IO_Onur_Oğuzlar_34_20260711_112846.json",
      "username": "Onur",
      "seflik": "Oğuzlar",
      "bolme": "34",
      "backup_date": "20260711",
      "backup_time": "112846",
      "created_at": "2026-07-11T08:28:47.699Z",
      "size_bytes": 29163,
      "view_url": "https://drive.google.com/file/d/1NXgFpuzxtRcAtlAXxXIcsVMGArcrUbA9/view",
      "download_url": "https://drive.google.com/uc?export=download&id=1NXgFpuzxtRcAtlAXxXIcsVMGArcrUbA9"
    },
    {
      "id": "1CDb2y-chHMrjM4_baylAoOjfmgZc3Dw9",
      "file_name": "Mesaha_IO_Onur_Oğuzlar_102_20260711_104030.json",
      "username": "Onur",
      "seflik": "Oğuzlar",
      "bolme": "102",
      "backup_date": "20260711",
      "backup_time": "104030",
      "created_at": "2026-07-11T07:40:31.431Z",
      "size_bytes": 33111,
      "view_url": "https://drive.google.com/file/d/1CDb2y-chHMrjM4_baylAoOjfmgZc3Dw9/view",
      "download_url": "https://drive.google.com/uc?export=download&id=1CDb2y-chHMrjM4_baylAoOjfmgZc3Dw9"
    },
    {
      "id": "12o7vXBFJ2xtaMQ2aNxOKK1HWmZFoxaq0",
      "file_name": "Mesaha_IO_Yakup_Yaylacık_454_20260710_235313.json",
      "username": "Yakup",
      "seflik": "Yaylacık",
      "bolme": "454",
      "backup_date": "20260710",
      "backup_time": "235313",
      "created_at": "2026-07-10T20:53:13.973Z",
      "size_bytes": 6871,
      "view_url": "https://drive.google.com/file/d/12o7vXBFJ2xtaMQ2aNxOKK1HWmZFoxaq0/view",
      "download_url": "https://drive.google.com/uc?export=download&id=12o7vXBFJ2xtaMQ2aNxOKK1HWmZFoxaq0"
    },
    {
      "id": "1a5EtVN5h-g4AOOnVgYwXLuALaID3lnFI",
      "file_name": "Mesaha_IO_Yasin_Yaylacık_454_20260710_235139.json",
      "username": "Yasin",
      "seflik": "Yaylacık",
      "bolme": "454",
      "backup_date": "20260710",
      "backup_time": "235139",
      "created_at": "2026-07-10T20:51:39.805Z",
      "size_bytes": 5740,
      "view_url": "https://drive.google.com/file/d/1a5EtVN5h-g4AOOnVgYwXLuALaID3lnFI/view",
      "download_url": "https://drive.google.com/uc?export=download&id=1a5EtVN5h-g4AOOnVgYwXLuALaID3lnFI"
    },
    {
      "id": "1Q7xDdwSJUs90MEh68DVWJEzf8kQEdOLM",
      "file_name": "Mesaha_IO_Yakup_Yaylacık_454_20260710_235029.json",
      "username": "Yakup",
      "seflik": "Yaylacık",
      "bolme": "454",
      "backup_date": "20260710",
      "backup_time": "235029",
      "created_at": "2026-07-10T20:50:30.923Z",
      "size_bytes": 3868,
      "view_url": "https://drive.google.com/file/d/1Q7xDdwSJUs90MEh68DVWJEzf8kQEdOLM/view",
      "download_url": "https://drive.google.com/uc?export=download&id=1Q7xDdwSJUs90MEh68DVWJEzf8kQEdOLM"
    },
    {
      "id": "13KeiFyZBKeagBOyCCQQpJM8wcIQ84nJu",
      "file_name": "Mesaha_IO_Mehmet Kırmızıgül_Karacakaya_5_20260710_090314.json",
      "username": "Mehmet Kırmızıgül",
      "seflik": "Karacakaya",
      "bolme": "5",
      "backup_date": "20260710",
      "backup_time": "090314",
      "created_at": "2026-07-10T06:03:15.383Z",
      "size_bytes": 1198,
      "view_url": "https://drive.google.com/file/d/13KeiFyZBKeagBOyCCQQpJM8wcIQ84nJu/view",
      "download_url": "https://drive.google.com/uc?export=download&id=13KeiFyZBKeagBOyCCQQpJM8wcIQ84nJu"
    },
    {
      "id": "1gD9qucU8lwU1VXoHN8jIs0w4h5dvB4aP",
      "file_name": "Mesaha_IO_Selda_Tavşanlı_bolme_20260709_164948.json",
      "username": "Selda",
      "seflik": "Tavşanlı",
      "bolme": "bolme",
      "backup_date": "20260709",
      "backup_time": "164948",
      "created_at": "2026-07-09T13:49:49.169Z",
      "size_bytes": 151749,
      "view_url": "https://drive.google.com/file/d/1gD9qucU8lwU1VXoHN8jIs0w4h5dvB4aP/view",
      "download_url": "https://drive.google.com/uc?export=download&id=1gD9qucU8lwU1VXoHN8jIs0w4h5dvB4aP"
    },
    {
      "id": "1chVlE4ZlNLGJNR96C_t1nOiBGcnD3U0U",
      "file_name": "Mesaha_IO_Taha_Tunçbilek_bolme_20260709_085123.json",
      "username": "Taha",
      "seflik": "Tunçbilek",
      "bolme": "bolme",
      "backup_date": "20260709",
      "backup_time": "085123",
      "created_at": "2026-07-09T05:51:24.524Z",
      "size_bytes": 2882,
      "view_url": "https://drive.google.com/file/d/1chVlE4ZlNLGJNR96C_t1nOiBGcnD3U0U/view",
      "download_url": "https://drive.google.com/uc?export=download&id=1chVlE4ZlNLGJNR96C_t1nOiBGcnD3U0U"
    },
    {
      "id": "1Mt2SFYmsuTJyxzQC0EQIRih_96sXxtA8",
      "file_name": "Mesaha_IO_Taha_Tunçbilek_bolme_20260709_085037.json",
      "username": "Taha",
      "seflik": "Tunçbilek",
      "bolme": "bolme",
      "backup_date": "20260709",
      "backup_time": "085037",
      "created_at": "2026-07-09T05:50:37.990Z",
      "size_bytes": 2882,
      "view_url": "https://drive.google.com/file/d/1Mt2SFYmsuTJyxzQC0EQIRih_96sXxtA8/view",
      "download_url": "https://drive.google.com/uc?export=download&id=1Mt2SFYmsuTJyxzQC0EQIRih_96sXxtA8"
    },
    {
      "id": "1I1ou260GdY28ZBLdJA87RK6o_qn4ukUD",
      "file_name": "Mesaha_IO_mehmettaskin01_Çınarlıdere_20_20260709_083424.json",
      "username": "mehmettaskin01",
      "seflik": "Çınarlıdere",
      "bolme": "20",
      "backup_date": "20260709",
      "backup_time": "083424",
      "created_at": "2026-07-09T05:34:25.595Z",
      "size_bytes": 207837,
      "view_url": "https://drive.google.com/file/d/1I1ou260GdY28ZBLdJA87RK6o_qn4ukUD/view",
      "download_url": "https://drive.google.com/uc?export=download&id=1I1ou260GdY28ZBLdJA87RK6o_qn4ukUD"
    },
    {
      "id": "12ToQg_5IQ60dqnE-1rfj_PHyqEyoJ-4z",
      "file_name": "Mesaha_IO_Hasan_4divan_bolme_20260708_170212.json",
      "username": "Hasan",
      "seflik": "4divan",
      "bolme": "bolme",
      "backup_date": "20260708",
      "backup_time": "170212",
      "created_at": "2026-07-08T14:02:13.671Z",
      "size_bytes": 3129,
      "view_url": "https://drive.google.com/file/d/12ToQg_5IQ60dqnE-1rfj_PHyqEyoJ-4z/view",
      "download_url": "https://drive.google.com/uc?export=download&id=12ToQg_5IQ60dqnE-1rfj_PHyqEyoJ-4z"
    }
  ]
}