{
  "app": "Mesaha İO",
  "version": "v550_yakupp",
  "build": 550,
  "visibleVersion": "V5.50 •Yakupp•",
  "shortVersion": "V5.50",
  "name": "Mesaha İO V5.50 •Yakupp•",
  "cacheName": "mio-app-v550-yakupp",
  "integrityId": "v550-existing-session-unblock-admin-login-r1",
  "builtAt": "2026-07-12T01:20:00+03:00",
  "notes": "Google geçişinde mevcut girişli cihazların eski kullanıcı/IP/cihaz engelleriyle yanlış kilitlenmesi önlendi. Onaylı Google kullanıcılarında kesin engel yalnız doğrulanmış user_id veya erişim kapatma üzerinden uygulanır. Admin hatalı girişleri loglanır ancak süreli giriş kilidi şimdilik kaldırıldı.",
  "assetVersion": "550",
  "latestVersion": "v550_yakupp",
  "latestBuild": 550,
  "currentBuild": 550,
  "minSupportedBuild": 409,
  "forceUpdate": false,
  "updateUrl": "./guncelle.html",
  "cleanUrl": "./temizle.html",
  "version_id": "v550_yakupp",
  "versionId": "v550_yakupp",
  "id": "v550_yakupp",
  "updated_at": "2026-07-12T01:20:00+03:00"
}
